{"topicId":3756,"forumId":122,"topicTitle":"Minor_Chaos:RDM","topicTime":1314144457,"topicViews":39,"topicReplies":1,"topicStatus":1,"topicFirstPosterName":"Playerhata27","topicFirstPosterColor":"009900","topicLastPosterName":"Chopper","topicLastPosterColor":"990000","topicLastPostTime":1314154078,"posts":[{"postId":30677,"topicId":3756,"posterId":812,"postTime":1314144457,"postText":"Offender name?:Minor_Chaos\nWhich Server?:TTT\nOffender's Steam ID?:STEAM_0:1:41482019\nWhat the Offender did?:He's RDM'd multiple times today and yesterday, funnily enough both the screenshots I have are on gm_SouthPark but two different days. He's killed on suspicion when we specifically told him that's against the rules.\nAdmins on?:Nope.\nProof?:\n http://i52.tinypic.com/21l389k.jpg \n http://i53.tinypic.com/35a6f86.jpg \n http://i54.tinypic.com/2nbc078.jpg \n http://i56.tinypic.com/15hio85.jpg \n http://i54.tinypic.com/2pyc413.jpg "},{"postId":30692,"topicId":3756,"posterId":84,"postTime":1314154078,"postText":"Ben you should lock ban requests when you are done with them >.>"}]}