{"topicId":205,"forumId":19,"topicTitle":"Bug in VIP Package and others","topicTime":1275493578,"topicViews":37,"topicReplies":1,"topicStatus":0,"topicFirstPosterName":"Mak_-","topicFirstPosterColor":"","topicLastPosterName":"No Refunds","topicLastPosterColor":"","topicLastPostTime":1275566596,"posts":[{"postId":1989,"topicId":205,"posterId":55,"postTime":1275493578,"postText":" #1 - I'm VIP on flood mod and im supposed to have like humm material tool , Colour , Noclip and etc. But I can only use Keep Upright :|.\n\n#2 - We can buy Time grenade and C4 and its supposed to be for Superadmin and TMP and AK is supposed to be for  Respected (VIP) "},{"postId":2049,"topicId":205,"posterId":12,"postTime":1275566596,"postText":"Dunno immot on the admin for jail, stranded,or flood yet. Once I am and am better at coding I would help you out."}]}