{"topicId":2224,"forumId":105,"topicTitle":"Rewards for playing","topicTime":1301207063,"topicViews":111,"topicReplies":1,"topicStatus":0,"topicFirstPosterName":"TinfoilHatter","topicFirstPosterColor":"FF6600","topicLastPosterName":"๖Mr. Gash","topicLastPosterColor":"000000","topicLastPostTime":1301210277,"posts":[{"postId":17924,"topicId":2224,"posterId":464,"postTime":1301207063,"postText":"Get on and play a bit!\nIf I'm on, I'll reward you with DIAMONDS.\nIf not, Pirate or Kry might be persuaded to give you some.\n\nThe server is functional for the first time in a while, and it'd be nice to see the popularity and player numbers we had a while ago.\nWe've also got shiny new plugins, my favorite one being /lastseen, which tells you when someone was last on.\n\nOn top of this, I'll be giving rewards for well-built structures, and there'll be regular contests.\n\nThere's a pretty large announcement due out from the admins this week as well, so stay tuned for it.\nI'm excited for it.\n\n--Tin ;)"},{"postId":17925,"topicId":2224,"posterId":2,"postTime":1301210277,"postText":"On to goldcraft we go."}]}