{"topicId":101,"forumId":26,"topicTitle":"*Clears Throat*","topicTime":1273369508,"topicViews":284,"topicReplies":20,"topicStatus":1,"topicFirstPosterName":"Ungrateful Dead","topicFirstPosterColor":"","topicLastPosterName":"No Refunds","topicLastPosterColor":"","topicLastPostTime":1273540532,"posts":[{"postId":813,"topicId":101,"posterId":39,"postTime":1273369508,"postText":"I am the Ungrateful Dead\nI'm a dead guy and I'm very ungrateful about it\nSo anyway\nLove your servers and stuff"},{"postId":814,"topicId":101,"posterId":26,"postTime":1273371984,"postText":"I'v seen you on it alot, Awesome player :D"},{"postId":815,"topicId":101,"posterId":12,"postTime":1273372963,"postText":"Welcome.... To sex land!!!! Hahaha let the rape from my sniper begin!"},{"postId":828,"topicId":101,"posterId":3,"postTime":1273374990,"postText":">> \nI'm a dead guy and I'm very ungrateful about it\n \n\nAgreed"},{"postId":833,"topicId":101,"posterId":4,"postTime":1273377355,"postText":"Welcome to NoGeeksJustNerds\n(lol)\n\nRead the rules before posting."},{"postId":840,"topicId":101,"posterId":153,"postTime":1273409616,"postText":">> Kryzoid\":2i82oshh]\nWelcome to NoGeeksJustNerds\n(lol)\n\nRead the rules before posting.\n \nKRYZOID STOP SPELLING IT WRONG!! >:O"},{"postId":842,"topicId":101,"posterId":12,"postTime":1273412453,"postText":"typos for me occur on ipods only not her..... dam,"},{"postId":860,"topicId":101,"posterId":3,"postTime":1273422104,"postText":"Yea kryzoid, you grammar nazi."},{"postId":862,"topicId":101,"posterId":39,"postTime":1273422503,"postText":">> \nYea kryzoid, you grammar nazi.\n \n\n http://rc.vc/forum/grammar-nazi.jpg "},{"postId":881,"topicId":101,"posterId":12,"postTime":1273437940,"postText":"win!!! just pure win"},{"postId":921,"topicId":101,"posterId":2,"postTime":1273461647,"postText":">> \n>> \nYea kryzoid, you grammar nazi.\n \n\n http://rc.vc/forum/grammar-nazi.jpg \n \n http://media.comicvine.com/uploads/2/27874/600107-oh_you_super.jpg "},{"postId":926,"topicId":101,"posterId":12,"postTime":1273491898,"postText":"Ol."},{"postId":938,"topicId":101,"posterId":153,"postTime":1273522787,"postText":"L.O.L."},{"postId":941,"topicId":101,"posterId":3,"postTime":1273522908,"postText":">> \n>> \n>> \nYea kryzoid, you grammar nazi.\n \n\n http://rc.vc/forum/grammar-nazi.jpg \n \n http://media.comicvine.com/uploads/2/27874/600107-oh_you_super.jpg \n \n http://www.playkon.com/uploads/2008/02/No-U.jpg "},{"postId":949,"topicId":101,"posterId":39,"postTime":1273525807,"postText":">> \n>> \n>> \n>> \nYea kryzoid, you grammar nazi.\n \n\n http://rc.vc/forum/grammar-nazi.jpg \n \n http://media.comicvine.com/uploads/2/27874/600107-oh_you_super.jpg \n \n http://www.playkon.com/uploads/2008/02/No-U.jpg \n \n http://www.comedysite.net/plugins/p17_image_gallery/images/1052.jpg "},{"postId":952,"topicId":101,"posterId":2,"postTime":1273526973,"postText":">> \n>> \n>> \n>> \n>> \nYea kryzoid, you grammar nazi.\n \n\n http://rc.vc/forum/grammar-nazi.jpg \n \n http://media.comicvine.com/uploads/2/27874/600107-oh_you_super.jpg \n \n http://www.playkon.com/uploads/2008/02/No-U.jpg \n \n http://www.comedysite.net/plugins/p17_image_gallery/images/1052.jpg \n \n http://rlv.zcache.com/llama_oh_no_the_drama_llama_followed_you_home_tshirt-p2355264953313475493fn0_400.jpg "},{"postId":954,"topicId":101,"posterId":39,"postTime":1273527121,"postText":">> \n>> \n>> \n>> \n>> \n>> \nYea kryzoid, you grammar nazi.\n \n\n http://rc.vc/forum/grammar-nazi.jpg \n \n http://media.comicvine.com/uploads/2/27874/600107-oh_you_super.jpg \n \n http://www.playkon.com/uploads/2008/02/No-U.jpg \n \n http://www.comedysite.net/plugins/p17_image_gallery/images/1052.jpg \n \n http://rlv.zcache.com/llama_oh_no_the_drama_llama_followed_you_home_tshirt-p2355264953313475493fn0_400.jpg \n \n http://www.halolz.com/wp-content/uploads/2007/11/oshi.jpg "},{"postId":961,"topicId":101,"posterId":4,"postTime":1273532820,"postText":">> \n>> \n>> \n>> \n>> \n>> \n>> \nYea kryzoid, you grammar nazi.\n \n\n http://rc.vc/forum/grammar-nazi.jpg \n \n http://media.comicvine.com/uploads/2/27874/600107-oh_you_super.jpg \n \n http://www.playkon.com/uploads/2008/02/No-U.jpg \n \n http://www.comedysite.net/plugins/p17_image_gallery/images/1052.jpg \n \n http://rlv.zcache.com/llama_oh_no_the_drama_llama_followed_you_home_tshirt-p2355264953313475493fn0_400.jpg \n \n http://www.halolz.com/wp-content/uploads/2007/11/oshi.jpg \n \n http://i40.tinypic.com/24gm32g.png "},{"postId":970,"topicId":101,"posterId":12,"postTime":1273539886,"postText":"bleh gurgle noo homo sla p you"},{"postId":972,"topicId":101,"posterId":4,"postTime":1273540029,"postText":"/lock\n\n\n...for obvious reasons"},{"postId":977,"topicId":101,"posterId":12,"postTime":1273540532,"postText":"good call kryzoid mah man"}]}