{"topicId":2423,"forumId":105,"topicTitle":"WHY WE AREN'T OPEN","topicTime":1303361042,"topicViews":116,"topicReplies":4,"topicStatus":1,"topicFirstPosterName":"Pirate43","topicFirstPosterColor":"FF6600","topicLastPosterName":"MZP.inferno","topicLastPosterColor":"","topicLastPostTime":1304676554,"posts":[{"postId":19358,"topicId":2423,"posterId":456,"postTime":1303361042,"postText":"still working on the new map and getting plugins and server to work properly, not only with 1.4 features, but now with 1.5. ah, the pain of being an admin xD\n\nif requested, will post screen on progress of central city 2.0 (which is very sexy btw)"},{"postId":20936,"topicId":2423,"posterId":272,"postTime":1304653171,"postText":"I know it's a deadpost, but *request*"},{"postId":20938,"topicId":2423,"posterId":373,"postTime":1304653442,"postText":">> I know it's a deadpost, but *request* \n\n/Request"},{"postId":20940,"topicId":2423,"posterId":456,"postTime":1304654496,"postText":"why request screenshots when you can take your own once we open tomorrow or early morning saturday? ;)"},{"postId":20950,"topicId":2423,"posterId":521,"postTime":1304676554,"postText":"Open fastar"}]}