{"topicId":3262,"forumId":105,"topicTitle":"Aether Mod added to Goldcraft","topicTime":1311114486,"topicViews":129,"topicReplies":3,"topicStatus":1,"topicFirstPosterName":"TinfoilHatter","topicFirstPosterColor":"FF6600","topicLastPosterName":"Kryzoid","topicLastPosterColor":"000099","topicLastPostTime":1311132538,"posts":[{"postId":25882,"topicId":3262,"posterId":464,"postTime":1311114486,"postText":"Just kidding, we're baiting James into reading this.\n\nNow that you are, James, get online and spleef or forfeit your place in the tournament."},{"postId":25884,"topicId":3262,"posterId":84,"postTime":1311125240,"postText":"That is a cruel fucking joke man."},{"postId":25886,"topicId":3262,"posterId":636,"postTime":1311127516,"postText":"LOL FUCK U TINFOIL :D UR EVIL <3"},{"postId":25889,"topicId":3262,"posterId":4,"postTime":1311132538,"postText":">> That is a cruel fucking joke man. \nWell, it ended up working."}]}