{"topicId":3557,"forumId":1,"topicTitle":"NNJG REAL LIFE PICS THREAD. O:","topicTime":1313011658,"topicViews":3981,"topicReplies":267,"topicStatus":0,"topicFirstPosterName":"ChocolatePanda","topicFirstPosterColor":"","topicLastPosterName":"[NNJG]Ben","topicLastPosterColor":"000000","topicLastPostTime":1319981477,"posts":[{"postId":28444,"topicId":3557,"posterId":1,"postTime":1313011658,"postText":"This thread is for people to have a chance to show who they really are. The majority of you hide behind icons and cartoons and Lua is curious to how you all look. This is the time to show me the goodies =0 ;)"},{"postId":28447,"topicId":3557,"posterId":1,"postTime":1313012561,"postText":">> This thread is for people to have a chance to show who they really are. The majority of you hide behind icons and cartoons and Lua is curious to how you all look. This is the time to show me the goodies =0 ;) \n\nIt also has to be recent, within the last year is the latest."},{"postId":28448,"topicId":3557,"posterId":705,"postTime":1313012885,"postText":"Well, seeing as i am your registered e-pimp ill have to just put this here.\nhttps://lh6.googleusercontent.com/-s8UB_7lVriM/TkL7FrCpSZI/AAAAAAAAAAU/ZVcAk01XO8I/s128/2011-08-10%25252000.20.33.jpg-toosmall\nhttps://picasaweb.google.com/112142949546807876189/DropBox?authkey=Gv1sRgCM_frsjDqrTXQw#5639345758293019026"},{"postId":28450,"topicId":3557,"posterId":916,"postTime":1313013010,"postText":"Im Fat. No Pics For You >:|"},{"postId":28451,"topicId":3557,"posterId":142,"postTime":1313013224,"postText":"Since Luam forced me too ;~;\n\n http://img38.imageshack.us/img38/552/image1vmy.jpg  \n\nUploaded with ImageShack.us "},{"postId":28452,"topicId":3557,"posterId":572,"postTime":1313013318,"postText":"I have no face"},{"postId":28453,"topicId":3557,"posterId":1,"postTime":1313013352,"postText":">> Im Fat. No Pics For You >:| \n I'm fat and I have my picture up =D"},{"postId":28454,"topicId":3557,"posterId":693,"postTime":1313013718,"postText":" http://i1196.photobucket.com/albums/aa403/necromancer14/Snapshot_20110426.jpg \n\nBecause my flipping the bird at people is the BEST picture I ever took."},{"postId":28456,"topicId":3557,"posterId":488,"postTime":1313014294,"postText":"http://tinypic.com/r/2wn233a/7\n\nIt's also my steam avatar."},{"postId":28457,"topicId":3557,"posterId":252,"postTime":1313014632,"postText":"These where from back in 2009. \n http://i51.tinypic.com/euewrr.jpg \n http://i52.tinypic.com/o70htl.jpg "},{"postId":28458,"topicId":3557,"posterId":377,"postTime":1313014711,"postText":"But, this is what I really look like 0-_0- Fear the Epic Lamprey!!!!"},{"postId":28459,"topicId":3557,"posterId":665,"postTime":1313014845,"postText":" http://i790.photobucket.com/albums/yy190/Mongo_2000/253610_1566789308378_1794783357_1011942_787822_n.jpg?t=1313014798 \n\nMe and my little sister when she graduated kindergarten last may.\n\n http://i790.photobucket.com/albums/yy190/Mongo_2000/280432_10150394216788782_717683781_10771734_8210814_o1-1.jpg?t=1313015201 \n\nMe catching the BIGGEST GODDAMN FISH you have ever seen caught at 7 in the morning."},{"postId":28461,"topicId":3557,"posterId":693,"postTime":1313016066,"postText":">> \n http://i790.photobucket.com/albums/yy190/Mongo_2000/280432_10150394216788782_717683781_10771734_8210814_o1-1.jpg?t=1313015201 \n\nMe catching the BIGGEST GODDAMN FISH you have ever seen caught at 7 in the morning. \n\nPFFT-\n\nI can catch fish bigger than that FROM A FUCKING FISHBOWL MOTHAFUCKA"},{"postId":28471,"topicId":3557,"posterId":101,"postTime":1313017838,"postText":"I was going to but Gash can't take a joke.\n\n And Punked is Kira and I don't want to die. "},{"postId":28474,"topicId":3557,"posterId":397,"postTime":1313018238,"postText":" http://i1137.photobucket.com/albums/n511/smoogly/th_realifepic2.png \nme and my gf\n\n http://i1137.photobucket.com/albums/n511/smoogly/th_reallifepic1.png \nyes ladies that is a 6inch tongue"},{"postId":28475,"topicId":3557,"posterId":693,"postTime":1313018731,"postText":">>  http://i1137.photobucket.com/albums/n511/smoogly/th_realifepic2.png  \n\nHey\n HEY \n  HEY  \n\nI'm the only blonde guy aloud 'round here."},{"postId":28476,"topicId":3557,"posterId":243,"postTime":1313019248,"postText":" http://images.memegenerator.net/instances/260x260/8462806.jpg \n  For disclosed reasons this picture has been edited for the general public.  "},{"postId":28484,"topicId":3557,"posterId":397,"postTime":1313020708,"postText":"^ ive already seen you on facebook\n\npssst his name realy is raffael\n\nhence funny raff"},{"postId":28485,"topicId":3557,"posterId":243,"postTime":1313020991,"postText":">> ^ ive already seen you on facebook\n\npssst his name realy is raffael\n\nhence funny raff \nYou spelt it wrong.\nAnd either way, It may or may not be a woman's name."},{"postId":28496,"topicId":3557,"posterId":272,"postTime":1313024045,"postText":"Just now (with timestamp)\n http://www.picdrop.net/images/P1010782.JPG \n\nBack in May\n http://www.picdrop.net/images/P1010759.jpg \n\n#swag"},{"postId":28497,"topicId":3557,"posterId":101,"postTime":1313024884,"postText":"Kobooold is sexy."},{"postId":28498,"topicId":3557,"posterId":1,"postTime":1313025617,"postText":">>  http://i1137.photobucket.com/albums/n511/smoogly/th_realifepic2.png \nme and my gf\n\n http://i1137.photobucket.com/albums/n511/smoogly/th_reallifepic1.png \nyes ladies that is a 6inch tongue \n\nhahaha nice"},{"postId":28499,"topicId":3557,"posterId":272,"postTime":1313025760,"postText":">> Kobooold is sexy. \nI concur with this statement. Now where are your pictures?"},{"postId":28500,"topicId":3557,"posterId":1,"postTime":1313025800,"postText":">> These where from back in 2009. \n http://i51.tinypic.com/euewrr.jpg \n http://i52.tinypic.com/o70htl.jpg  \n\n\nthat ish looks awesome!... what is it called? O_O"},{"postId":28501,"topicId":3557,"posterId":1,"postTime":1313025867,"postText":">> Kobooold is sexy. \n\nI agree, you are cute."},{"postId":28504,"topicId":3557,"posterId":252,"postTime":1313026039,"postText":">> that ish looks awesome!... what is it called? O_O \nTop one is Barret M82.\nThe other one is M2 Browning.\nThey both use 50 cal. BMG."},{"postId":28505,"topicId":3557,"posterId":101,"postTime":1313027047,"postText":">> >> Kobooold is sexy. \nI concur with this statement. Now where are your pictures? \n\n\nI seriously do not have any recent ones that don't make me look like a complete faggot. My facebook has either very old ones or really bad ones. Theres maybe one but that is from a few years ago."},{"postId":28506,"topicId":3557,"posterId":586,"postTime":1313027378,"postText":">> These where from back in 2009. \n http://i51.tinypic.com/euewrr.jpg \n http://i52.tinypic.com/o70htl.jpg  \n\nAint that a 1919?\n\nOr am I mistaken?\n\n<bottom one>"},{"postId":28507,"topicId":3557,"posterId":272,"postTime":1313027420,"postText":"Take one now :D"},{"postId":28508,"topicId":3557,"posterId":612,"postTime":1313027522,"postText":" http://www.picdrop.net/images/270260_1975981593302_1055953104_31861383_2590418_n.jpg the girl on the right was my prom date."},{"postId":28509,"topicId":3557,"posterId":101,"postTime":1313027699,"postText":">> Take one now :D \n\nNo camera.\n\n\n@Corey Do we have to have a sexy-off? KOB vs COREY"},{"postId":28510,"topicId":3557,"posterId":252,"postTime":1313027915,"postText":">> \nAint that a 1919?\n\nOr am I mistaken?\n\n<bottom one> \nNope, Mau-Duce.  http://en.wikipedia.org/wiki/M2_Browning "},{"postId":28511,"topicId":3557,"posterId":665,"postTime":1313028043,"postText":"-snip-"},{"postId":28515,"topicId":3557,"posterId":272,"postTime":1313029576,"postText":">> >> Take one now :D \n\nNo camera.\n\n\n@Corey Do we have to have a sexy-off? KOB vs COREY \n\n*dances inappropriately*"},{"postId":28517,"topicId":3557,"posterId":612,"postTime":1313030303,"postText":">> >> >> Take one now :D \n\nNo camera.\n\n\n@Corey Do we have to have a sexy-off? KOB vs COREY \n\n*dances inappropriately* \n@dum yes\n@kob\n*takes hand, square dances*"},{"postId":28518,"topicId":3557,"posterId":272,"postTime":1313030433,"postText":"*spins corey*"},{"postId":28520,"topicId":3557,"posterId":142,"postTime":1313030608,"postText":"One I just took right now or at this moment in time.\n\n http://img15.imageshack.us/img15/8284/image2xp.jpg  \n\nUploaded with ImageShack.us "},{"postId":28521,"topicId":3557,"posterId":1,"postTime":1313030922,"postText":">> One I just took right now or at this moment in time.\n\n http://img15.imageshack.us/img15/8284/image2xp.jpg  \n\nUploaded with ImageShack.us  \n\n\nLMAO WIN!"},{"postId":28522,"topicId":3557,"posterId":272,"postTime":1313031327,"postText":">> One I just took right now or at this moment in time.\n\n-snip-\n\nUploaded with ImageShack.us  \n\nTotal badass."},{"postId":28524,"topicId":3557,"posterId":364,"postTime":1313033519,"postText":"I used to have pictures of my self, but got rid of them a long time ago."},{"postId":28527,"topicId":3557,"posterId":115,"postTime":1313035384,"postText":"I'd post one, but I don't have anywhere to upload it to right now."},{"postId":28530,"topicId":3557,"posterId":272,"postTime":1313035665,"postText":">> I'd post one, but I don't have anywhere to upload it to right now. \npicdrop.net \n(unless you mean computer wise)"},{"postId":28532,"topicId":3557,"posterId":115,"postTime":1313035747,"postText":"No computer, lol.\n\nAlso I'm blonde- dirty blonde as well."},{"postId":28533,"topicId":3557,"posterId":272,"postTime":1313036130,"postText":">> No computer, lol.\n\nAlso I'm blonde- dirty blonde as well. \n http://www.picdrop.net/images/sdfg.jpg \ndone"},{"postId":28535,"topicId":3557,"posterId":115,"postTime":1313036316,"postText":"Close, except my hair isn't so long, it much closer to short short. :3"},{"postId":28536,"topicId":3557,"posterId":272,"postTime":1313036446,"postText":" http://www.picdrop.net/images/ap0yHk.jpg \nfixed"},{"postId":28537,"topicId":3557,"posterId":115,"postTime":1313036591,"postText":"MMMMM, much better."},{"postId":28538,"topicId":3557,"posterId":272,"postTime":1313036694,"postText":" http://www.picdrop.net/images/jF9uD5.jpg "},{"postId":28539,"topicId":3557,"posterId":82,"postTime":1313037244,"postText":"Will put up pictures whenever I get back home, a few days to a week"},{"postId":28540,"topicId":3557,"posterId":586,"postTime":1313037926,"postText":">> >> \nAint that a 1919?\n\nOr am I mistaken?\n\n<bottom one> \nNope, Mau-Duce.  http://en.wikipedia.org/wiki/M2_Browning  \n\nhow the fuck you afford that?"},{"postId":28541,"topicId":3557,"posterId":272,"postTime":1313038027,"postText":"I reaaaalllly doubt he bought it. xD"},{"postId":28543,"topicId":3557,"posterId":101,"postTime":1313038127,"postText":" http://i55.tinypic.com/10p7mdj.jpg \nDum's foot. <3 Playerhata.\n\nEDIT: Resized."},{"postId":28544,"topicId":3557,"posterId":235,"postTime":1313038325,"postText":"Dum :O i thought I raised you better then to go showing off your foot to the internet."},{"postId":28545,"topicId":3557,"posterId":237,"postTime":1313038763,"postText":"a quick pic moon took with his phone in a mirror. \n http://dl.dropbox.com/u/870345/NNJG/IMG_20110810_225414.jpg \n\nMoon is too damn tired to smile :P"},{"postId":28547,"topicId":3557,"posterId":634,"postTime":1313040089,"postText":"Moon your phone is fucking boss. I'll edit this to have my pic tommorow.\n\nEDIT: I just posted it. on a different post. Problem?"},{"postId":28548,"topicId":3557,"posterId":517,"postTime":1313040699,"postText":" http://i1088.photobucket.com/albums/i338/nblckk/photo.jpg  7 months ago hope it works enjoy it ;)"},{"postId":28549,"topicId":3557,"posterId":101,"postTime":1313040903,"postText":">>  http://s1088.photobucket.com/albums/i338/nblckk/?action=view&current=photo.jpg  7 months ago hope it works enjoy it ;) \n\n\nPhotobucket doesnt work."},{"postId":28550,"topicId":3557,"posterId":272,"postTime":1313040961,"postText":"It works, just right click the image and copy image url."},{"postId":28551,"topicId":3557,"posterId":586,"postTime":1313041162,"postText":"I'd use my phone to take one but I do not have a USB cable for it, and I'm on my iPod :P"},{"postId":28552,"topicId":3557,"posterId":101,"postTime":1313041698,"postText":">> I'd use my phone to take one but I do not have a USB cable for it, and I'm on my iPod :P \n\n\nYou can usually email it to yourself from your phone, as I did with mine."},{"postId":28558,"topicId":3557,"posterId":586,"postTime":1313043939,"postText":"Not possible\n\n>has no data plan"},{"postId":28559,"topicId":3557,"posterId":101,"postTime":1313044190,"postText":"I dont think I have one either, just try it."},{"postId":28560,"topicId":3557,"posterId":586,"postTime":1313045013,"postText":"I did, gives me error \"Omar: no response\""},{"postId":28562,"topicId":3557,"posterId":586,"postTime":1313045599,"postText":"*sorry for double post* dum, pm me your email so I can send it to you"},{"postId":28567,"topicId":3557,"posterId":464,"postTime":1313053355,"postText":" http://k.min.us/il4RGM.jpg \n\nHi playerhata."},{"postId":28570,"topicId":3557,"posterId":1,"postTime":1313061525,"postText":"what is with the feet?! O_O\n\nMakes me feel like posting a pic of my feet...\n\nha"},{"postId":28576,"topicId":3557,"posterId":595,"postTime":1313069736,"postText":">> what is with the feet?! O_O\n\nMakes me feel like posting a pic of my feet...\n\nha \n\nIt all started with playahater..."},{"postId":28581,"topicId":3557,"posterId":115,"postTime":1313071538,"postText":"These feet....why."},{"postId":28582,"topicId":3557,"posterId":54,"postTime":1313072120,"postText":"fuck real life pictures, WHERE'S THE FUCKIN FEET AT? \n(this doesn't go towards anyone that already posted feet, I love Tin and Dum.)"},{"postId":28583,"topicId":3557,"posterId":377,"postTime":1313072360,"postText":" http://i1103.photobucket.com/albums/g461/ryumaruborike/Picture0012.jpg \nBecause I don't own a Razor"},{"postId":28589,"topicId":3557,"posterId":54,"postTime":1313074673,"postText":" http://i56.tinypic.com/fvk9dl.jpg \n http://i51.tinypic.com/29awv1z.png \n http://i53.tinypic.com/25qf801.jpg \n\nyeah, im fat. fat swag. umad?"},{"postId":28594,"topicId":3557,"posterId":595,"postTime":1313079352,"postText":"Mark we still love your fatass.\nJk. Your not fat bro."},{"postId":28597,"topicId":3557,"posterId":634,"postTime":1313079827,"postText":" http://i877.photobucket.com/albums/ab332/Destar_01/IMG_0336.jpg?t=1313079755 \nMore white guys with blonde hair. hurrah."},{"postId":28604,"topicId":3557,"posterId":112,"postTime":1313083502,"postText":"Low quality webcam. Like i give a fuck.\n http://i.imgur.com/eeMTU.png "},{"postId":28606,"topicId":3557,"posterId":54,"postTime":1313083873,"postText":">> Low quality webcam. Like i give a fuck.\n http://i.imgur.com/eeMTU.png  \nCoolface.jpg?"},{"postId":28607,"topicId":3557,"posterId":272,"postTime":1313084018,"postText":"Nice picture Pharaoh. Gonna go play poker with your stuffed animals? ;D"},{"postId":28612,"topicId":3557,"posterId":112,"postTime":1313086015,"postText":">> Nice picture Pharaoh. Gonna go play poker with your stuffed animals? ;D \nhuh?"},{"postId":28619,"topicId":3557,"posterId":272,"postTime":1313088254,"postText":"Got your sunglasses on, got your \"I don't even give a fuck\" face, and I made an insinuation that you don't have friends. :3"},{"postId":28620,"topicId":3557,"posterId":634,"postTime":1313088406,"postText":"Oh! Can i be the first one to put someone's face on something else?\n http://i877.photobucket.com/albums/ab332/Destar_01/phar.png "},{"postId":28621,"topicId":3557,"posterId":272,"postTime":1313089682,"postText":"My turn!\n(Only doing one due to the fact that if I did more I would just be a dick, since I made one of you, do whatever you want with mine)\n http://www.picdrop.net/images/datass4374126107lhl.png "},{"postId":28622,"topicId":3557,"posterId":377,"postTime":1313089961,"postText":" http://i1103.photobucket.com/albums/g461/ryumaruborike/PonyPharoah.png "},{"postId":28625,"topicId":3557,"posterId":112,"postTime":1313092303,"postText":">>  http://i1103.photobucket.com/albums/g461/ryumaruborike/PonyPharoah.png  \nThe fuck is that. \nNeeds more Rainbow Dash."},{"postId":28632,"topicId":3557,"posterId":812,"postTime":1313093377,"postText":"All these feet have amused me, thank you Lua.\n\nAlso, still waiting on yours Lua............"},{"postId":28636,"topicId":3557,"posterId":235,"postTime":1313093809,"postText":"my epic photo enhancing skills\n \n\n http://img801.imageshack.us/img801/6145/unledefe.png \n\n\nwell maybe not"},{"postId":28642,"topicId":3557,"posterId":1,"postTime":1313094751,"postText":"You guys aren't as ugly as I figured you probably would be. lol\n\n\nplayer....soon enough...soon enough"},{"postId":28655,"topicId":3557,"posterId":377,"postTime":1313101164,"postText":">> >>  http://i1103.photobucket.com/albums/g461/ryumaruborike/PonyPharoah.png  \nThe fuck is that. \nNeeds more Rainbow Dash. \nAS YOU WISH\n http://i1103.photobucket.com/albums/g461/ryumaruborike/sam.jpg "},{"postId":28657,"topicId":3557,"posterId":82,"postTime":1313101442,"postText":"Well there be a storm brewin'', can't do anything but laptop for now.\n\n    smokin'' tokin'' grillin'' chillin''    \n http://i.imgur.com/TUd8P.png \n    afterwards    \n http://i.imgur.com/WSgvd.jpg "},{"postId":28665,"topicId":3557,"posterId":82,"postTime":1313102624,"postText":" http://i.imgur.com/TJiZG.jpg \n    Me, doing what appears to be reaching down a young boys pantaloons, but it actually is.     "},{"postId":28671,"topicId":3557,"posterId":373,"postTime":1313103752,"postText":" http://img402.imageshack.us/img402/134/yeahthasmeproblem.jpg \n\nOld picture is old. Found it on a disc, pwoblem?"},{"postId":28675,"topicId":3557,"posterId":812,"postTime":1313106536,"postText":"JESUS FUCK, DOMINEETO I AM LOL'ing SO FUCKING HARD.\n\nAlso, damn, Barenti, you sexy boi."},{"postId":28681,"topicId":3557,"posterId":769,"postTime":1313107711,"postText":"YES. YES. OH GOD YES."},{"postId":28682,"topicId":3557,"posterId":364,"postTime":1313108064,"postText":"_Crisis?"},{"postId":28697,"topicId":3557,"posterId":1,"postTime":1313112730,"postText":">>  http://img402.imageshack.us/img402/134/yeahthasmeproblem.jpg \n\nOld picture is old. Found it on a disc, pwoblem? \n\nheeeeelllloooooo Balenti ;)"},{"postId":28698,"topicId":3557,"posterId":1,"postTime":1313112803,"postText":">> _Crisis? \n\nHe got an admin to delete his, so no more crisis."},{"postId":28700,"topicId":3557,"posterId":48,"postTime":1313113236,"postText":"My hair is getting kinda long, needs a trim soon.\nThis pic is also about a month old but w/e, it's good enough.\n\n http://img16.imageshack.us/img16/1808/1040039.jpg "},{"postId":28703,"topicId":3557,"posterId":377,"postTime":1313114246,"postText":">> My hair is getting kinda long, needs a trim soon.\nThis pic is also about a month old but w/e, it's good enough.\n \nU Jelly\n http://i1103.photobucket.com/albums/g461/ryumaruborike/Picture0013.jpg "},{"postId":28705,"topicId":3557,"posterId":4,"postTime":1313114827,"postText":"Well, this picture is kind of old, but here you guys go.\n\n http://i.min.us/ilM8Pu.png "},{"postId":28708,"topicId":3557,"posterId":769,"postTime":1313115249,"postText":">> Well, this picture is kind of old, but here you guys go. Dammnn gurl, you're looking sexy"},{"postId":28726,"topicId":3557,"posterId":634,"postTime":1313118832,"postText":"Balenti, Corey, and Kob are the trifecta of smexyness."},{"postId":28728,"topicId":3557,"posterId":142,"postTime":1313119161,"postText":">> Balenti, Corey, and Kob are the trifecta of smexyness. \n^ Lulululul kay"},{"postId":28729,"topicId":3557,"posterId":373,"postTime":1313119205,"postText":"Koboold actually looks like someone I know.. Elijah?! Is that you, Elijah?!\n\nAnd yes Boom, I am one of the triforce of smexyness. Pwoblem?"},{"postId":28738,"topicId":3557,"posterId":397,"postTime":1313120662,"postText":">> Balenti, Corey, and Kob are the trifecta of smexyness. \n\n\nD:\n\n\n6 inch tongue and im smooglez"},{"postId":28740,"topicId":3557,"posterId":142,"postTime":1313120896,"postText":"I am my own smexyness >:D"},{"postId":28744,"topicId":3557,"posterId":634,"postTime":1313121602,"postText":"Smooglez, you're too special to be grouped up with other people in a trifecta."},{"postId":28746,"topicId":3557,"posterId":54,"postTime":1313122218,"postText":"I can't tell if That Guy is trolling or not with his pictures.."},{"postId":28748,"topicId":3557,"posterId":272,"postTime":1313122341,"postText":">> Koboold actually looks like someone I know.. Elijah?! Is that you, Elijah?!\n\nAnd yes Boom, I am one of the triforce of smexyness. Pwoblem? \n\n\nSorry, my name's Drew.\n\n@smooglez As long as your tongue leaves your mouth, it doesn't matter. lulululul"},{"postId":28750,"topicId":3557,"posterId":665,"postTime":1313122712,"postText":"I catch fish and have a little sister that I could hook up with player."},{"postId":28751,"topicId":3557,"posterId":48,"postTime":1313123370,"postText":"Fuck your trifecta of smexiness. I alone output more smexiness."},{"postId":28753,"topicId":3557,"posterId":272,"postTime":1313124092,"postText":"Don't be badmouthing the Trifecta, or we gon'' FIIIIIIND you."},{"postId":28754,"topicId":3557,"posterId":142,"postTime":1313124735,"postText":">> Fuck your trifecta of smexiness. I alone output more smexiness. \nThis."},{"postId":28755,"topicId":3557,"posterId":373,"postTime":1313125697,"postText":">> I can't tell if That Guy is trolling or not with his pictures.. \n\nNo it's real I remember him posting a thread about the things he bought such as, a headcrab hat.. a Katana and somethin'' else. \nBut thasshim"},{"postId":28758,"topicId":3557,"posterId":1,"postTime":1313127034,"postText":" http://www.picdrop.net/images/1543531015013399dld.jpg \nThis was lua in 2006 of sophomore year. D=\n\n http://www.picdrop.net/images/21706410150263789822.jpg \nThis was lua in 2009 senior year.D=\n\n http://www.picdrop.net/images/18469310150190041467.jpg \nThis is lua without makeup. D=\n\n http://www.picdrop.net/images/22177710150276947147.jpg \nAnd this is lua now. =D"},{"postId":28774,"topicId":3557,"posterId":115,"postTime":1313155423,"postText":"Dom is a pedo"},{"postId":28792,"topicId":3557,"posterId":82,"postTime":1313164056,"postText":">> Dom is a pedo \nPics or it didn't happen."},{"postId":28820,"topicId":3557,"posterId":735,"postTime":1313170869,"postText":" http://www.picdrop.net/images/10435112926872473816.jpg \nBack when I was like 10-11. With Jay Novacek.\n http://www.picdrop.net/images/17540106840835995327.jpg \nFarthest to the left, blue shirt. ~6\n http://www.picdrop.net/images/22501521697201166521.jpg \nLast year reading a book. I rarely do that.Lol"},{"postId":28838,"topicId":3557,"posterId":634,"postTime":1313174355,"postText":"Aimbot what are you doing!?! There's a computer right behind you in that last picture, next time get on TTT while no one's looking."},{"postId":28842,"topicId":3557,"posterId":706,"postTime":1313174914,"postText":" http://www.picdrop.net/images/26241110126824989109.jpg "},{"postId":28843,"topicId":3557,"posterId":397,"postTime":1313175111,"postText":"-snip- \n\n\nby myself"},{"postId":28851,"topicId":3557,"posterId":735,"postTime":1313177495,"postText":">> Aimbot what are you doing!?! There's a computer right behind you in that last picture, next time get on TTT while no one's looking. \nThey have a filter that bans everything.We cant download anything either"},{"postId":28855,"topicId":3557,"posterId":101,"postTime":1313179346,"postText":"I've seen a picture of Tin majestically planking before. He is hawt."},{"postId":28868,"topicId":3557,"posterId":1,"postTime":1313185270,"postText":">>  http://www.picdrop.net/images/26241110126824989109.jpg  \n\n;)"},{"postId":28873,"topicId":3557,"posterId":718,"postTime":1313187127,"postText":"My new myspace pic.\n\nYea check dat swag.\n\n http://a2.l3-images.myspacecdn.com/images02/75/83b4a3df7d3540ef95169c5f507b22c8/m.jpg "},{"postId":28874,"topicId":3557,"posterId":812,"postTime":1313187194,"postText":"If that really is you Toxic, you sexy motherfucker."},{"postId":28878,"topicId":3557,"posterId":665,"postTime":1313187998,"postText":">> myspace \n\nHAHAHAHAHAHAHAHAHHAHAHAHAAH"},{"postId":28881,"topicId":3557,"posterId":735,"postTime":1313188837,"postText":">> >> myspace \n\nHAHAHAHAHAHAHAHAHHAHAHAHAAH \n i c what you did thar"},{"postId":28888,"topicId":3557,"posterId":54,"postTime":1313190984,"postText":">> >> myspace \n\nHAHAHAHAHAHAHAHAHHAHAHAHAAH "},{"postId":28896,"topicId":3557,"posterId":718,"postTime":1313193185,"postText":" http://imageshack.us/photo/my-images/51/purplelz.jpg/ \nhttp://imageshack.us/photo/my-images/51/purplelz.jpg/\nits what purple looks like. amirite?"},{"postId":28897,"topicId":3557,"posterId":876,"postTime":1313193285,"postText":"hmmmmm should I post minnneeee?"},{"postId":28900,"topicId":3557,"posterId":634,"postTime":1313193873,"postText":">>  http://imageshack.us/photo/my-images/51/purplelz.jpg/ \nhttp://imageshack.us/photo/my-images/51/purplelz.jpg/\nits what purple looks like. amirite? \nOH GOD PURPLE IS A BROKEN IMAGE!? OH THE HORROR!"},{"postId":28901,"topicId":3557,"posterId":876,"postTime":1313195352,"postText":" http://i.imgur.com/PUtFt.jpg \nYAMAHA FTW\nno wait\nSUZUKI FTW."},{"postId":28903,"topicId":3557,"posterId":272,"postTime":1313195841,"postText":"Mudkip is awesome."},{"postId":28906,"topicId":3557,"posterId":397,"postTime":1313196447,"postText":"mudkip go to radio shack and buy a 15 dollar mic\n\nif you say nou i say nou back"},{"postId":28907,"topicId":3557,"posterId":876,"postTime":1313196554,"postText":"I already have a mic though...;_;"},{"postId":28932,"topicId":3557,"posterId":456,"postTime":1313203077,"postText":"That pic of tin majestically planking is hilariously dumb -.-\n\nthis is the one and only pic you all will get of the pirate. \nhttp://i.min.us/iecvjDmhj.JPG"},{"postId":28935,"topicId":3557,"posterId":4,"postTime":1313203644,"postText":">> That pic of tin majestically planking is hilariously dumb -.-\n\nthis is the one and only pic you all will get of the pirate. \nhttp://i.min.us/iecvjDmhj.JPG \nis that the old one from that movie thing? i don't remember you having that suit so i think it is."},{"postId":28937,"topicId":3557,"posterId":456,"postTime":1313203863,"postText":"it is. [TRAWLAWLAWL at communicating via forums as opposed to directly since we are not more than 10 feet away]\n\nEdit:\nupon closer inspection of my own pic, DAT CLEFT :D"},{"postId":28938,"topicId":3557,"posterId":1,"postTime":1313204228,"postText":">> My new myspace pic.\n\nYea check dat swag.\n\n http://a2.l3-images.myspacecdn.com/images02/75/83b4a3df7d3540ef95169c5f507b22c8/m.jpg  \n\n\ndammmmn.....helllllloooooooo toxic"},{"postId":28950,"topicId":3557,"posterId":735,"postTime":1313207749,"postText":">>  http://imageshack.us/photo/my-images/51/purplelz.jpg/ \nhttp://imageshack.us/photo/my-images/51/purplelz.jpg/\nits what purple looks like. amirite? \nOH WTF"},{"postId":28962,"topicId":3557,"posterId":54,"postTime":1313213077,"postText":"KRYZOID, post your sexy ass."},{"postId":28989,"topicId":3557,"posterId":718,"postTime":1313239521,"postText":"lol jk that dude i posted a pic of has to be like 25-30 (im 17). Ill post a real pic of me in a little bit, i just searched for like \"Gangster Swagger\" or something on google images and found that dudes myspace.\n\nPirate be lookin like one classy mother fucker.\n\nEdit:\n http://i.imgur.com/5wIft.png \nIm not asian btw. My eyes were just barely open because it was taken at like 9am...\nIts blurry because i only have a shitty xbox live cam thing."},{"postId":28995,"topicId":3557,"posterId":456,"postTime":1313247901,"postText":">> \nPirate be lookin like one classy mother fucker.\n \n\nY thank U"},{"postId":29015,"topicId":3557,"posterId":636,"postTime":1313254179,"postText":"SHould i post a pic of me?"},{"postId":29016,"topicId":3557,"posterId":54,"postTime":1313254397,"postText":">> SHould i post a pic of me? \nYes."},{"postId":29104,"topicId":3557,"posterId":856,"postTime":1313280476,"postText":" http://img853.imageshack.us/img853/8886/img1993d.jpg \nThat is half of me, the other half is a troll."},{"postId":29120,"topicId":3557,"posterId":456,"postTime":1313282580,"postText":"I half expected you to be italian lol."},{"postId":29132,"topicId":3557,"posterId":856,"postTime":1313285093,"postText":">> I half expected you to be italian lol. \nWas it the Spaghetti? LOL"},{"postId":29173,"topicId":3557,"posterId":456,"postTime":1313295017,"postText":">> >> I half expected you to be italian lol. \nWas it the Spaghetti? LOL \n... MAYBE ... XD"},{"postId":29179,"topicId":3557,"posterId":1,"postTime":1313296448,"postText":">>  http://img853.imageshack.us/img853/8886/img1993d.jpg \nThat is half of me, the other half is a troll. \n\nlmao still <3 you"},{"postId":29203,"topicId":3557,"posterId":605,"postTime":1313322163,"postText":"Found a pic of me back in college. I hope it satisfies the curiosity of where the laugh comes from.\n\n http://i309.photobucket.com/albums/kk373/cyoungz/alienme.jpg "},{"postId":29206,"topicId":3557,"posterId":112,"postTime":1313324558,"postText":"Rotfl udane"},{"postId":29221,"topicId":3557,"posterId":272,"postTime":1313340012,"postText":"@Udane \n\nWhat the fuuuuu"},{"postId":29223,"topicId":3557,"posterId":101,"postTime":1313346654,"postText":"Kind of how I expected him to be."},{"postId":29230,"topicId":3557,"posterId":373,"postTime":1313348450,"postText":"I'm not surprised"},{"postId":29233,"topicId":3557,"posterId":812,"postTime":1313349378,"postText":"At least now we understand how he laughs like that.........."},{"postId":29241,"topicId":3557,"posterId":572,"postTime":1313355732,"postText":" http://img94.imageshack.us/img94/3214/lolhfl.png "},{"postId":29324,"topicId":3557,"posterId":456,"postTime":1313370754,"postText":">>  http://img94.imageshack.us/img94/3214/lolhfl.png  \none of the most disturbing things ive seen since Dr. Manhattan's penis."},{"postId":29349,"topicId":3557,"posterId":464,"postTime":1313377182,"postText":"The Tinfoil, planking at his finest:\n http://k.min.us/jjmvWs.JPG "},{"postId":29359,"topicId":3557,"posterId":612,"postTime":1313382188,"postText":" http://tapatalk.com/mu/46a19642-9f15-1137.jpg \n\nNew tattoo. Same on both shoulder blades. Got them today."},{"postId":29365,"topicId":3557,"posterId":1,"postTime":1313385848,"postText":">> Found a pic of me back in college. I hope it satisfies the curiosity of where the laugh comes from.\n\n http://i309.photobucket.com/albums/kk373/cyoungz/alienme.jpg  \n\n\n-_- I screamed when I saw this...."},{"postId":29366,"topicId":3557,"posterId":1,"postTime":1313385917,"postText":">>  http://tapatalk.com/mu/46a19642-9f15-1137.jpg \n\nNew tattoo. Same on both shoulder blades. Got them today. \n\n\nwhy it is bleeding so bad?!"},{"postId":29376,"topicId":3557,"posterId":101,"postTime":1313390303,"postText":"Because it's a tattoo... everybody bleeds when they get a tattoo."},{"postId":29406,"topicId":3557,"posterId":945,"postTime":1313424592,"postText":"Hm. Maybe I'll post a pic when I get back.\nAnd Udane, ಠ_ಠ."},{"postId":29435,"topicId":3557,"posterId":375,"postTime":1313436881,"postText":"Hello, this post just got twenty-seven times awesomer."},{"postId":29472,"topicId":3557,"posterId":1,"postTime":1313447292,"postText":">> Because it's a tattoo... everybody bleeds when they get a tattoo. \n\nMy tats didn't bleed..."},{"postId":29473,"topicId":3557,"posterId":101,"postTime":1313448500,"postText":"Most do."},{"postId":29475,"topicId":3557,"posterId":612,"postTime":1313449885,"postText":"Mine bled for hours.RIP two of my white tees"},{"postId":29547,"topicId":3557,"posterId":1,"postTime":1313464242,"postText":">> Mine bled for hours. I RIP two of my white tees \n\n O_O\nTIME FOR MORE TATTOOS!!! =D"},{"postId":29578,"topicId":3557,"posterId":272,"postTime":1313472455,"postText":">> Mine bled for hours. I RIP two of my white tees  I read that before reading about the tattoos and wtf'd."},{"postId":29592,"topicId":3557,"posterId":1,"postTime":1313518295,"postText":">> >> Mine bled for hours. I RIP two of my white tees  I read that before reading about the tattoos and wtf'd. \n\nlmao"},{"postId":29709,"topicId":3557,"posterId":959,"postTime":1313615538,"postText":">> Don't be badmouthing the Trifecta, or we gon'' FIIIIIIND you. \n\nYo I am the most SMEXIEST HERE! I just dont have a picture of it, only pic I hav of me is my current spray but its from 8th grade and i look Wayyyyy better. :("},{"postId":29778,"topicId":3557,"posterId":82,"postTime":1313681662,"postText":" http://www.google.ca/url?source=imglanding&ct=img&q=http://files.turbosquid.com/Preview/Content_2009_07_16__17_01_41/sperm_cell.jpg0c2a3bbc-600e-4111-bb71-70f41749d489Larger.jpg&sa=X&ei=vjBNTtPyLafViAKn8JGWAQ&ved=0CAUQ8wc&usg=AFQjCNHI5Vr-LLFyW1UBA7NAJUollbmuEw \n\n Baby photo, those were the days. "},{"postId":29795,"topicId":3557,"posterId":968,"postTime":1313694656,"postText":" http://media.nscdn.com/uploads/site/news/13112689463684/coc_12.jpg \n\nSteez."},{"postId":29914,"topicId":3557,"posterId":82,"postTime":1313776073,"postText":" http://i.imgur.com/igXeZ.jpg  http://i.imgur.com/HcbZu.jpg  http://i.imgur.com/OpFcF.jpg "},{"postId":30376,"topicId":3557,"posterId":754,"postTime":1313980075,"postText":" http://i1178.photobucket.com/albums/x366/thecappiman/16436_1294865611740_1233307272_910902_6728719_n.jpg \nthe only one I could find that was good quality. and yes that is a $80 sweater that I got for $10 :3"},{"postId":30444,"topicId":3557,"posterId":1,"postTime":1314045870,"postText":">>  http://i.imgur.com/igXeZ.jpg  http://i.imgur.com/HcbZu.jpg  http://i.imgur.com/OpFcF.jpg  \n\n\nwtf lmao"},{"postId":31019,"topicId":3557,"posterId":988,"postTime":1314483963,"postText":"I'll only post my pic if Player puts his up first!"},{"postId":31050,"topicId":3557,"posterId":968,"postTime":1314498849,"postText":">> I'll only post my pic if Player puts his up first! \n\n\nThis..."},{"postId":31077,"topicId":3557,"posterId":1,"postTime":1314504720,"postText":">> I'll only post my pic if Player puts his up first! \n\n\nWouldn't he just post his feet?"},{"postId":31080,"topicId":3557,"posterId":812,"postTime":1314505661,"postText":"Well, this is awkward."},{"postId":31091,"topicId":3557,"posterId":735,"postTime":1314508558,"postText":">> Wouldn't he just post his feet? \nI don't think he has a fetish of his own feet. That means he would be a narcis feet sistic"},{"postId":31093,"topicId":3557,"posterId":1,"postTime":1314510601,"postText":">> >> Wouldn't he just post his feet? \nI don't think he has a fetish of his own feet. That means he would be a narcis feet sistic \n  \n\nhahahahahahaha"},{"postId":31348,"topicId":3557,"posterId":735,"postTime":1314662598,"postText":"Come on guys, don't be so shy."},{"postId":31351,"topicId":3557,"posterId":4,"postTime":1314662798,"postText":">> Come on guys, don't be so shy. \nShut up ;_;"},{"postId":31395,"topicId":3557,"posterId":956,"postTime":1314671274,"postText":"I gots no pics So AHA :P"},{"postId":32813,"topicId":3557,"posterId":945,"postTime":1315630542,"postText":"-snip-"},{"postId":32818,"topicId":3557,"posterId":54,"postTime":1315632940,"postText":"anyway, purple is really really pretty, js c:"},{"postId":32835,"topicId":3557,"posterId":595,"postTime":1315657460,"postText":">> anyway, purple is really really pretty, js c: \n\nI second this."},{"postId":32836,"topicId":3557,"posterId":612,"postTime":1315660131,"postText":"Meh, id hit dat pengu doe"},{"postId":32839,"topicId":3557,"posterId":82,"postTime":1315663342,"postText":"She kind of looks like Karen Gillian, which is a good thing :)"},{"postId":32867,"topicId":3557,"posterId":101,"postTime":1315686092,"postText":"Do you have a penguin for a shoulder?"},{"postId":32896,"topicId":3557,"posterId":945,"postTime":1315693779,"postText":"Yes. Yes I do."},{"postId":32901,"topicId":3557,"posterId":612,"postTime":1315696907,"postText":"In that case......\n\n\n\n\nI can haz Dutch rudder?"},{"postId":32905,"topicId":3557,"posterId":79,"postTime":1315697358,"postText":"Lets keep this pg13 Corey"},{"postId":32949,"topicId":3557,"posterId":76,"postTime":1315715028,"postText":"Me\n\nFirst picture, i'm second from the right.\n http://i.imgur.com/GVGBp.jpg  \n http://i.imgur.com/HzaCB.png  \n http://i.imgur.com/bUR6N.png  \n\n\nHAF A PIC OF MY HAMSTER LOL\n\n http://i.imgur.com/807yp.png  "},{"postId":32953,"topicId":3557,"posterId":612,"postTime":1315717760,"postText":">> Lets keep this pg13 Corey \nOkay. Hey little girl. Can I shake ....\nThere's no way to say that in a pg13 tone sorry."},{"postId":32977,"topicId":3557,"posterId":945,"postTime":1315748335,"postText":"Well this is awkward."},{"postId":32980,"topicId":3557,"posterId":665,"postTime":1315748845,"postText":">> Me\n\nFirst picture, i'm second from the right.\n http://i.imgur.com/GVGBp.jpg  \n http://i.imgur.com/HzaCB.png  \n http://i.imgur.com/bUR6N.png   \n\nDo you know how to smile?"},{"postId":32993,"topicId":3557,"posterId":945,"postTime":1315761469,"postText":"Yeah Region! Why so srs? :c"},{"postId":33005,"topicId":3557,"posterId":76,"postTime":1315769214,"postText":">> Yeah Region! Why so srs? :c \n\n\nsmiling is for babies and the weak"},{"postId":33006,"topicId":3557,"posterId":76,"postTime":1315769351,"postText":">> Yeah Region! Why so srs? :c  IS THIS GUD ENUF :*( uiswe  I SMILED\n\n http://i.imgur.com/al40H.jpg  "},{"postId":33010,"topicId":3557,"posterId":373,"postTime":1315773306,"postText":" http://t0.gstatic.com/images?q=tbn:ANd9GcT3GrytvzRp3Jj_Vf4Q9-Pp_WJFd6BcXFewt5mPzqU_MU3IPI0c "},{"postId":33015,"topicId":3557,"posterId":634,"postTime":1315778505,"postText":" http://i877.photobucket.com/albums/ab332/Destar_01/srsregion.png \nfixed"},{"postId":33103,"topicId":3557,"posterId":694,"postTime":1315835606,"postText":" http://i.imgur.com/JHvoD.jpg  \n\nthe allmighty jesus revealed... he's actually nyan man"},{"postId":33188,"topicId":3557,"posterId":373,"postTime":1315889157,"postText":"Is that a gay pride rainbow flag?"},{"postId":33210,"topicId":3557,"posterId":115,"postTime":1315937616,"postText":">> Is that a gay pride rainbow flag? \nThis man.\n\nHe  is angel  knows."},{"postId":33228,"topicId":3557,"posterId":694,"postTime":1315957101,"postText":">> Is that a gay pride rainbow flag? \n\nwhy yes it is my good chap not gay myself though,  just went to this gay pride party thing boy do those guys no how to party =D  \n\nI <3 gay people =P"},{"postId":33418,"topicId":3557,"posterId":1061,"postTime":1316284446,"postText":" http://i54.tinypic.com/a9qlh2.jpg "},{"postId":33424,"topicId":3557,"posterId":612,"postTime":1316285531,"postText":"I'll be dumping soon. So you can see what i look like outside the tuxedo."},{"postId":33428,"topicId":3557,"posterId":1094,"postTime":1316289102,"postText":"Here it is!  The picture no one asked for or wanted, but I'm giving it to you anyway!\n http://i665.photobucket.com/albums/vv19/flameboy1132/Snapshot_20110917.jpg \nI don't have any silly stuff to wear or poses to do, sorry.\nEDIT: Sorry for the kinda dim lighting.  Too lazy to get up :/"},{"postId":33451,"topicId":3557,"posterId":79,"postTime":1316304232,"postText":"^.... The next mass murderer everyone. Just look at how he wants cold blooded murder on his hands."},{"postId":33458,"topicId":3557,"posterId":82,"postTime":1316315091,"postText":"Dude he looks like Rory off the newest seasons of Doctor Who, Purple looks like Amy and I will the the Doctor\n\n http://i.imgur.com/p3Dzt.png  http://media.steampowered.com/steamcommunity/public/images/avatars/4a/4a92c93aae77071e3bbe4eb175786b231cbbd712_full.jpg \nTom Baker"},{"postId":33469,"topicId":3557,"posterId":1094,"postTime":1316318383,"postText":"Who looks like Rory? Me? Oh, and thanks for saying I look like a serial killer, crisis >:/\nI just can't smile easily for pictures, it feels so unnatural.  Oh well, most pictures look worse than that.  And that's really your face (on the left) Domineeto? Epic derp look on your face."},{"postId":33479,"topicId":3557,"posterId":82,"postTime":1316322366,"postText":" http://i.imgur.com/SUKY9.png \nAnd yes, yes it is."},{"postId":33480,"topicId":3557,"posterId":243,"postTime":1316326251,"postText":"Why is there lemonade all over your shoulder?"},{"postId":33487,"topicId":3557,"posterId":612,"postTime":1316336434,"postText":"Bad attempt at fire glow, try feathering it and turning opacity down some."},{"postId":33493,"topicId":3557,"posterId":82,"postTime":1316354433,"postText":">> Bad attempt at fire glow, try feathering it and turning opacity down some. \nI use Paint.net, dinglederp. I would have looked for some add-ons for doing that but I was too lazy."},{"postId":33506,"topicId":3557,"posterId":612,"postTime":1316369085,"postText":"Nah brah ya suck. :p"},{"postId":35024,"topicId":3557,"posterId":1122,"postTime":1318013005,"postText":" http://a2.sphotos.ak.fbcdn.net/hphotos-ak-snc7/293694_255202854514032_100000729574797_819911_4410036_n.jpg \nI watch you sleep."},{"postId":35193,"topicId":3557,"posterId":292,"postTime":1318227204,"postText":"Why is this in miscellaneous games\nWhy is luam's name suddenly chocolate panda or whatever\nWhy did this guy just bump a month-old topic\nI'M SO CONFUSED!!"},{"postId":35195,"topicId":3557,"posterId":373,"postTime":1318230808,"postText":"Topics aren't \"officially\" dead until it's been 2 months since the last post, or if it gets severely off-topic. I demand mooor pics for my entertainment"},{"postId":35201,"topicId":3557,"posterId":517,"postTime":1318252575,"postText":" http://i52.tinypic.com/300xhsj.jpg \n\n\nDamn im hot"},{"postId":35204,"topicId":3557,"posterId":612,"postTime":1318258619,"postText":"You look like a waiter that works at a   gay bar  \n\nalso whats up with that lamp noclipping through your wall?\n\n http://a2.sphotos.ak.fbcdn.net/hphotos-ak-snc7/293694_255202854514032_100000729574797_819911_4410036_n.jpg \nand who is that guy"},{"postId":35208,"topicId":3557,"posterId":517,"postTime":1318262432,"postText":"Lamps an admin"},{"postId":35291,"topicId":3557,"posterId":1122,"postTime":1318433330,"postText":"I am Treecko."},{"postId":35293,"topicId":3557,"posterId":612,"postTime":1318437106,"postText":"WELL FUCK YOU, THEN"},{"postId":35378,"topicId":3557,"posterId":988,"postTime":1318547835,"postText":">> I am Treecko. \n\nNo! You're ChipMcDip"},{"postId":35379,"topicId":3557,"posterId":1122,"postTime":1318548073,"postText":"Fine, but I have Treecko's pics on ransom."},{"postId":35394,"topicId":3557,"posterId":735,"postTime":1318557464,"postText":">> >> I am Treecko. \n\nNo! You're ChipMcDip \nOther users posting from this IP\nChipMcdip [ 1 Post ]"},{"postId":35396,"topicId":3557,"posterId":735,"postTime":1318557730,"postText":">> It was obviously a joke Aimbot -____- \nNo shit."},{"postId":35398,"topicId":3557,"posterId":82,"postTime":1318561086,"postText":">> \nNo shit. \n>> 4. You must respect your fellow clan members and staff.\n9. If you have nothing constructive to add, don't add anything. \nPlease follow forum rules."},{"postId":35438,"topicId":3557,"posterId":968,"postTime":1318658195,"postText":" http://a7.sphotos.ak.fbcdn.net/hphotos-ak-snc6/248121_2106404376646_1141634477_4185034_6437282_n.jpg "},{"postId":35631,"topicId":3557,"posterId":1097,"postTime":1318905585,"postText":"My pic\n http://img577.imageshack.us/img577/1175/unledgdg.png  \n\nUploaded with ImageShack.us \n\nLast time before saying good bye to my country\n\nP.S: It's my cousin's kid that I'm holding"},{"postId":35660,"topicId":3557,"posterId":1094,"postTime":1318912647,"postText":"We still haven't seen what Player or Udane really look like! Also what's the deal with the whole ChipMcDip and Treecko thing?\n\nNutterButter you should post a pic too :D\n\nI plan on posting more if I can find an outfit that doesn't look like shit.  Maybe I'll do a Halloween one in a while here, that could be a cool theme."},{"postId":35667,"topicId":3557,"posterId":612,"postTime":1318928958,"postText":"^ dress up as a pumpkin. Like moms do to infants"},{"postId":35669,"topicId":3557,"posterId":612,"postTime":1318929282,"postText":">> My pic\n\n-snipped-\n\nLast time before saying good bye to my country\n\nP.S: It's my cousin's kid that I'm holding \n\n http://tapatalk.com/mu/46a19871-4370-8288.jpg "},{"postId":35688,"topicId":3557,"posterId":812,"postTime":1318964070,"postText":">> We still haven't seen what Player or Udane really look like! \n\n>> Found a pic of me back in college. I hope it satisfies the curiosity of where the laugh comes from.\n\n http://i309.photobucket.com/albums/kk373/cyoungz/alienme.jpg  "},{"postId":35698,"topicId":3557,"posterId":292,"postTime":1318978029,"postText":"I'd prefer to stay a mystery to all."},{"postId":36283,"topicId":3557,"posterId":153,"postTime":1319503395,"postText":">> I'd prefer to stay a mystery to all. "},{"postId":36284,"topicId":3557,"posterId":4,"postTime":1319503663,"postText":">> Ben\":38b5wtu7]I'd prefer to stay a mystery to all. \n\n http://i.minus.com/iMNy2REk76rmL.png "},{"postId":36291,"topicId":3557,"posterId":153,"postTime":1319506253,"postText":">> >> Ben\":3mjxg7j8]I'd prefer to stay a mystery to all. \n\n http://i.minus.com/iMNy2REk76rmL.png  \n<3"},{"postId":36299,"topicId":3557,"posterId":252,"postTime":1319511273,"postText":">> Ben\":1l54c3no]I'd prefer to stay a mystery to all. \n\n\n\nWe all know what you look like... =/"},{"postId":36303,"topicId":3557,"posterId":82,"postTime":1319512294,"postText":">> >> Ben\":1haqk207]I'd prefer to stay a mystery to all. \n\n\n\nWe all know what you look like... =/ \nI've never seen him, what does he look like?"},{"postId":36310,"topicId":3557,"posterId":1140,"postTime":1319515995,"postText":" http://i894.photobucket.com/albums/ac141/nicholsml/168226_1530373268439_1507961178_31142083_6080086_n.jpg \n\nMirror Mirror on the wall, who is the sexist of them all?\n\n(sorry about bad quality, stupid iphone 3G cameras. This was taken back in ''10)"},{"postId":36312,"topicId":3557,"posterId":373,"postTime":1319519145,"postText":">> >> >> Ben\":337mt680]I'd prefer to stay a mystery to all. \n\n\n\nWe all know what you look like... =/ \nI've never seen him, what does he look like? \n\nIf I were to show you my account would be terminated and I would be banned from nnjg forever. It's srs business"},{"postId":36319,"topicId":3557,"posterId":115,"postTime":1319546905,"postText":"Domineeto, stop that :S"},{"postId":36326,"topicId":3557,"posterId":612,"postTime":1319572900,"postText":"Me, koboold, punked, and quack know what Ben looks like. If I recall a certain thread.. Please don't ban me :S"},{"postId":36329,"topicId":3557,"posterId":153,"postTime":1319573130,"postText":">> Me, koboold, punked, and quack know what Ben looks like. If I recall a certain thread.. Please don't ban me :S \nKry does too(I video chatted w/ him once)\nI also know what Kry looks like.... O.o"},{"postId":36332,"topicId":3557,"posterId":612,"postTime":1319573342,"postText":"I know where kryzoid lives."},{"postId":36333,"topicId":3557,"posterId":4,"postTime":1319573534,"postText":"You saw me on a bad hair day :X\nAnd Corey, i know where you live too."},{"postId":36336,"topicId":3557,"posterId":612,"postTime":1319574648,"postText":"...what?D:"},{"postId":36338,"topicId":3557,"posterId":1140,"postTime":1319575466,"postText":"^\n\nStalkerfest....? \n\n\nNah."},{"postId":36349,"topicId":3557,"posterId":595,"postTime":1319580679,"postText":"I saw Ben on youtube pwoblem?"},{"postId":36352,"topicId":3557,"posterId":237,"postTime":1319583020,"postText":">> I saw Ben on youtube pwoblem? \nit was for me. o.o"},{"postId":36362,"topicId":3557,"posterId":735,"postTime":1319585307,"postText":">> >> I saw Ben on youtube pwoblem? \nit was for me. o.o \nI liked your youtube, Ben. :("},{"postId":36372,"topicId":3557,"posterId":82,"postTime":1319587669,"postText":">> Domineeto, stop that :S \nI have seen one picture of him, was that really him? The one with his face photoshoped on? The one that the one guy sent me"},{"postId":36396,"topicId":3557,"posterId":373,"postTime":1319599193,"postText":">> Ben\":v8lbamf6]I also know what Kry looks like.... O.o \n\npics or it didn't happen"},{"postId":36433,"topicId":3557,"posterId":115,"postTime":1319653064,"postText":">> >> Ben\":6a6smh0n]I also know what Kry looks like.... O.o \n\npics or it didn't happen \n\n http://nonerdsjustgeeks.com/forum/download/file.php?avatar=373_1314951279.jpg "},{"postId":36439,"topicId":3557,"posterId":4,"postTime":1319660879,"postText":"|\n|\n|\n<---"},{"postId":36485,"topicId":3557,"posterId":373,"postTime":1319694068,"postText":"That photo was shopped, I can tell from the pixels"},{"postId":36543,"topicId":3557,"posterId":82,"postTime":1319755875,"postText":"(pic removed)\nI don't get it, is there a 1 pixel picture or something?"},{"postId":36545,"topicId":3557,"posterId":4,"postTime":1319756142,"postText":"lol now the arrow is pointing at you. i am you now. problem?"},{"postId":36546,"topicId":3557,"posterId":101,"postTime":1319756379,"postText":"I really hope the second tab is a joke."},{"postId":36548,"topicId":3557,"posterId":153,"postTime":1319757138,"postText":">> I really hope the second tab is a joke. \nXD"},{"postId":36608,"topicId":3557,"posterId":1140,"postTime":1319777443,"postText":"LOL yes. Thats hilarious."},{"postId":36614,"topicId":3557,"posterId":1016,"postTime":1319780371,"postText":"LOL wow guess we know what he was doing/looking at. How do you recover from that?"},{"postId":36631,"topicId":3557,"posterId":634,"postTime":1319828611,"postText":">> LOL wow guess we know what he was doing/looking at. How do you recover from that? \nCan't tell if serious....."},{"postId":36637,"topicId":3557,"posterId":84,"postTime":1319838693,"postText":">> >> LOL wow guess we know what he was doing/looking at. How do you recover from that? \nCan't tell if serious..... \nI fear for the worst that he is D:"},{"postId":36702,"topicId":3557,"posterId":153,"postTime":1319981477,"postText":">> >> >> LOL wow guess we know what he was doing/looking at. How do you recover from that? \nCan't tell if serious..... \nI fear for the worst that he is D: \nI think your fear is right......"}]}