{"topicId":1929,"forumId":105,"topicTitle":"hell gates in goldcraft","topicTime":1297983272,"topicViews":141,"topicReplies":4,"topicStatus":0,"topicFirstPosterName":"Alphonse","topicFirstPosterColor":"","topicLastPosterName":"Alphonse","topicLastPosterColor":"","topicLastPostTime":1297987304,"posts":[{"postId":16065,"topicId":1929,"posterId":465,"postTime":1297983272,"postText":"i went on goldcraft today and tried to make a hell gate but i cant light the gate because flint and steel cant light fire.\nany help?"},{"postId":16068,"topicId":1929,"posterId":112,"postTime":1297984375,"postText":"I'm pretty sure the nether portals dont even work in smp"},{"postId":16069,"topicId":1929,"posterId":465,"postTime":1297984957,"postText":"the admins said that they were gana add gates when they changed servers\n\nand they changed servers"},{"postId":16071,"topicId":1929,"posterId":4,"postTime":1297986754,"postText":"correction: we said that it would be implemented this weekend."},{"postId":16072,"topicId":1929,"posterId":465,"postTime":1297987304,"postText":"yay to that\n\n\nand yay to ur 1000 post kry"}]}