{"topicId":809,"forumId":19,"topicTitle":"NEW FEATURE","topicTime":1284343116,"topicViews":83,"topicReplies":2,"topicStatus":0,"topicFirstPosterName":"[NNJG]Ben","topicFirstPosterColor":"000000","topicLastPosterName":"[NNJG]Ben","topicLastPosterColor":"000000","topicLastPostTime":1284375778,"posts":[{"postId":7559,"topicId":809,"posterId":153,"postTime":1284343116,"postText":"Hello,\nHave you noticed the new support button on the homepage?\nWell, if you EVER need an admin for server help, forum help, or anything, click that button. You will be forwarded to an online admin who can help you.\nNow you don't have to look through your friends list to find someone online, you can just click that button.\nAdmins can come talk to me for their accounts, Sanya and I have active ones as I am writing this.\n:D"},{"postId":7588,"topicId":809,"posterId":4,"postTime":1284348014,"postText":"really cool, but i hate it how the link for it is all over the forums. if you click on anywhere thats not already a link, you get sent to it."},{"postId":7594,"topicId":809,"posterId":153,"postTime":1284375778,"postText":"Not for me :/"}]}