{"topicId":677,"forumId":12,"topicTitle":"No votekick for pubbies.","topicTime":1282671732,"topicViews":103,"topicReplies":0,"topicStatus":0,"topicFirstPosterName":"Dum","topicFirstPosterColor":"000099","topicLastPosterName":"Dum","topicLastPosterColor":"000099","topicLastPostTime":1282671732,"posts":[{"postId":6066,"topicId":677,"posterId":101,"postTime":1282671732,"postText":"All it does is get abused... And EVERYONE has a feeling just to say yes, I have never seen one denied yet.\n\nEDIT: Err, sorry, this is supposed to go under Jail Suggestions. My bad."}]}